{
  "name": "DICOM Mammography Study",
  "layoutContents": {
    "RMLO": "<storage_item_id>",
    "LMLO": "<storage_item_id>",
    "RCC": "<storage_item_id>",
    "LCC": "<storage_item_id>"
  },
  "layout": {
    "direction": "column",
    "first": {
      "direction": "row",
      "first": {
        "key": "RMLO"
      },
      "second": {
        "key": "LMLO"
      },
      "splitPercentage": 50.0
    },
    "second": {
      "direction": "row",
      "first": {
        "key": "RCC"
      },
      "second": {
        "key": "LCC"
      },
      "splitPercentage": 50.0
    },
    "splitPercentage": 50.0
  },
  "$schema": "https://raw.githubusercontent.com/encord-team/Annotate/main/data-groups/data_group_schema.json"
}
